django_referer_breadcrumbs/__init__.py
django_referer_breadcrumbs/apps.py
django_referer_breadcrumbs/middleware.py
django_referer_breadcrumbs/templates/breadcrumbs-items.html
django_referer_breadcrumbs/templates/breadcrumbs.html
django_referer_breadcrumbs-0.0.2.dist-info/METADATA
django_referer_breadcrumbs-0.0.2.dist-info/WHEEL
django_referer_breadcrumbs-0.0.2.dist-info/licenses/LICENCE
django_referer_breadcrumbs-0.0.2.dist-info/RECORD
